render_html/__init__.py
render_html/_renderer.py
render_html/exceptions.py
render_html_v2-1.0.0.dist-info/LICENSE
render_html_v2-1.0.0.dist-info/METADATA
render_html_v2-1.0.0.dist-info/WHEEL
render_html_v2-1.0.0.dist-info/top_level.txt
render_html_v2-1.0.0.dist-info/RECORD
