Metadata-Version: 2.1
Name: render_html_v2
Version: 1.0.0
Summary: Python library that provides a simple way to render HTML content in a web browser.
Author-email: Emmanuel Bastidas <EmmanuelBastidas@tutanota.com>
Project-URL: Homepage, https://github.com/ank634/render-html
Project-URL: Bug Tracker, https://github.com/ank634/render-html/issues
Classifier: Programming Language :: Python :: 3
Classifier: License :: OSI Approved :: MIT License
Classifier: Operating System :: OS Independent
Requires-Python: >=3.10
License-File: LICENSE
